enablr_dashboard/__init__.py
enablr_dashboard/__main__.py
enablr_dashboard/cleaning_data.py
enablr_dashboard/connect.py
enablr_dashboard/db_action.py
enablr_dashboard/read_gdrive.py
enablr_dashboard-0.1.2.dist-info/WHEEL
enablr_dashboard-0.1.2.dist-info/METADATA
enablr_dashboard-0.1.2.dist-info/RECORD
