Metadata-Version: 2.1
Name: enablr-dashboard
Version: 0.1.2
Summary: Populate data from excel in gdrive enablr
Author: Khoerrizal
Author-email: khoerrizal@gmail.com
Requires-Python: >=3.9,<4.0
Classifier: Programming Language :: Python :: 3
Classifier: Programming Language :: Python :: 3.10
Classifier: Programming Language :: Python :: 3.9
Requires-Dist: CacheControl (==0.12.11)
Requires-Dist: Pygments (==2.12.0)
Requires-Dist: SQLAlchemy (==1.4.37)
Requires-Dist: asttokens (==2.0.5)
Requires-Dist: backcall (==0.2.0)
Requires-Dist: beautifulsoup4 (==4.11.1)
Requires-Dist: bleach (==5.0.0)
Requires-Dist: cachetools (==5.2.0)
Requires-Dist: cachy (==0.3.0)
Requires-Dist: certifi (==2022.5.18.1)
Requires-Dist: charset-normalizer (==2.0.12)
Requires-Dist: cleo (==0.8.1)
Requires-Dist: clikit (==0.6.2)
Requires-Dist: colorama (==0.4.4)
Requires-Dist: commonmark (==0.9.1)
Requires-Dist: crashtest (==0.3.1)
Requires-Dist: decorator (==5.1.1)
Requires-Dist: distlib (==0.3.4)
Requires-Dist: docutils (==0.18.1)
Requires-Dist: et-xmlfile (==1.1.0)
Requires-Dist: executing (==0.8.3)
Requires-Dist: filelock (==3.7.1)
Requires-Dist: google (==3.0.0)
Requires-Dist: google-api-core (==2.8.1)
Requires-Dist: google-api-python-client (==2.49.0)
Requires-Dist: google-auth (==2.6.6)
Requires-Dist: google-auth-httplib2 (==0.1.0)
Requires-Dist: googleapis-common-protos (==1.56.2)
Requires-Dist: greenlet (==1.1.2)
Requires-Dist: html5lib (==1.1)
Requires-Dist: httplib2 (==0.20.4)
Requires-Dist: idna (==3.3)
Requires-Dist: importlib-metadata (==4.11.4)
Requires-Dist: ipdb (==0.13.9)
Requires-Dist: ipython (==8.4.0)
Requires-Dist: jedi (==0.18.1)
Requires-Dist: keyring (==23.5.1)
Requires-Dist: lockfile (==0.12.2)
Requires-Dist: loguru (==0.6.0)
Requires-Dist: matplotlib-inline (==0.1.3)
Requires-Dist: msgpack (==1.0.3)
Requires-Dist: numpy (==1.22.4)
Requires-Dist: openpyxl (==3.0.10)
Requires-Dist: packaging (==20.9)
Requires-Dist: pandas (==1.4.2)
Requires-Dist: parso (==0.8.3)
Requires-Dist: pastel (==0.2.1)
Requires-Dist: pexpect (==4.8.0)
Requires-Dist: pickleshare (==0.7.5)
Requires-Dist: pkginfo (==1.8.2)
Requires-Dist: platformdirs (==2.5.2)
Requires-Dist: poetry (==1.1.13)
Requires-Dist: poetry-core (==1.0.8)
Requires-Dist: prompt-toolkit (==3.0.29)
Requires-Dist: protobuf (==3.20.1)
Requires-Dist: psycopg2-binary (==2.9.3)
Requires-Dist: ptyprocess (==0.7.0)
Requires-Dist: pure-eval (==0.2.2)
Requires-Dist: pyasn1 (==0.4.8)
Requires-Dist: pyasn1-modules (==0.2.8)
Requires-Dist: pylev (==1.4.0)
Requires-Dist: pyparsing (==3.0.9)
Requires-Dist: python-dateutil (==2.8.2)
Requires-Dist: pytz (==2022.1)
Requires-Dist: pywin32-ctypes (==0.2.0)
Requires-Dist: readme-renderer (==35.0)
Requires-Dist: requests (==2.27.1)
Requires-Dist: requests-toolbelt (==0.9.1)
Requires-Dist: rfc3986 (==2.0.0)
Requires-Dist: rich (==12.4.4)
Requires-Dist: rsa (==4.8)
Requires-Dist: shellingham (==1.4.0)
Requires-Dist: six (==1.16.0)
Requires-Dist: soupsieve (==2.3.2.post1)
Requires-Dist: stack-data (==0.2.0)
Requires-Dist: toml (==0.10.2)
Requires-Dist: tomlkit (==0.11.0)
Requires-Dist: traitlets (==5.2.2.post1)
Requires-Dist: twine (==4.0.1)
Requires-Dist: uritemplate (==4.1.1)
Requires-Dist: urllib3 (==1.26.9)
Requires-Dist: virtualenv (==20.14.1)
Requires-Dist: wcwidth (==0.2.5)
Requires-Dist: webencodings (==0.5.1)
Requires-Dist: win32-setctime (==1.1.0)
Requires-Dist: zipp (==3.8.0)
